videowall/__init__.py
videowall/browser.py
videowall/content.py
videowall/main.py
videowall/options.py
videowall/player.py
videowall/searchable_list.py
videowall/style.qss
videowall/video_wall.py
videowall/window.py
videowall-1.2.0.dist-info/licenses/LICENSE
videowall-1.2.0.dist-info/METADATA
videowall-1.2.0.dist-info/WHEEL
videowall-1.2.0.dist-info/entry_points.txt
videowall-1.2.0.dist-info/top_level.txt
videowall-1.2.0.dist-info/RECORD
