Metadata-Version: 2.4
Name: videowall
Version: 1.2.0
Summary: A Qt video wall player
Author-email: Robin Scher <robin@uberware.net>
Project-URL: Homepage, https://github.com/uberware/videowall
Requires-Python: >=3.9
License-File: LICENSE
Requires-Dist: PySide6>=6.7
Dynamic: license-file
